MANIFEST.in
README.txt
setup.cfg
setup.py
BlastOff.egg-info/PKG-INFO
BlastOff.egg-info/SOURCES.txt
BlastOff.egg-info/dependency_links.txt
BlastOff.egg-info/entry_points.txt
BlastOff.egg-info/not-zip-safe
BlastOff.egg-info/requires.txt
BlastOff.egg-info/top_level.txt
blastoff/__init__.py
blastoff/template/MANIFEST.in_tmpl
blastoff/template/README.txt_tmpl
blastoff/template/development.ini_tmpl
blastoff/template/ez_setup.py
blastoff/template/setup.cfg_tmpl
blastoff/template/setup.py_tmpl
blastoff/template/test.ini_tmpl
blastoff/template/+package+/__init__.py
blastoff/template/+package+/websetup.py_tmpl
blastoff/template/+package+/config/__init__.py
blastoff/template/+package+/config/deployment.ini_tmpl_tmpl
blastoff/template/+package+/config/environment.py_tmpl
blastoff/template/+package+/config/middleware.py_tmpl
blastoff/template/+package+/config/routing.py_tmpl
blastoff/template/+package+/config/who.ini_tmpl
blastoff/template/+package+/controllers/__init__.py
blastoff/template/+package+/controllers/account.py_tmpl
blastoff/template/+package+/controllers/admin.py_tmpl
blastoff/template/+package+/controllers/error.py_tmpl
blastoff/template/+package+/controllers/home.py_tmpl
blastoff/template/+package+/lib/__init__.py
blastoff/template/+package+/lib/app_globals.py_tmpl
blastoff/template/+package+/lib/base.py_tmpl
blastoff/template/+package+/lib/helpers.py
blastoff/template/+package+/model/__init__.py_tmpl
blastoff/template/+package+/model/meta.py
blastoff/template/+package+/model/forms/__init__.py
blastoff/template/+package+/model/forms/build.py_tmpl
blastoff/template/+package+/model/forms/validators.py_tmpl
blastoff/template/+package+/public/favicon.ico
blastoff/template/+package+/public/css/style.css
blastoff/template/+package+/public/images/BlastOff-header.png
blastoff/template/+package+/public/images/flash_alert.png
blastoff/template/+package+/public/images/flash_info.png
blastoff/template/+package+/public/images/flash_ok.png
blastoff/template/+package+/templates/home.mako_tmpl
blastoff/template/+package+/templates/account/login.mako
blastoff/template/+package+/templates/account/register.mako
blastoff/template/+package+/templates/base/base-index.mako_tmpl
