Metadata-Version: 1.0
Name: BlastOff
Version: 0.3a2
Summary: A Pylons application template providing a working site skeleton configured with SQLAlchemy, mako, repoze.who, ToscaWidgets, TurboMail, WebFlash and (optionally) SchemaBot. The generated app is pre-configured with authentication, login and registration forms, and (optionally) email confirmation.
Home-page: http://bitbucket.org/chrismiles/blastoff/
Author: Chris Miles
Author-email: miles.chris@gmail.com
License: MIT
Download-URL: http://pypi.python.org/pypi/BlastOff
Keywords: pylons,template,sqlalchemy,toscawidgets,mako,repoze.who,TurboMail,WebFlash,SchemaBot
Platform: UNKNOWN
